fabricio
